rctuiautomator2/__init__.py
rctuiautomator2/__main__.py
rctuiautomator2/_proto.py
rctuiautomator2/_selector.py
rctuiautomator2/abcd.py
rctuiautomator2/exceptions.py
rctuiautomator2/image.py
rctuiautomator2/init.py
rctuiautomator2/messagebox.py
rctuiautomator2/screenrecord.py
rctuiautomator2/settings.py
rctuiautomator2/swipe.py
rctuiautomator2/utils.py
rctuiautomator2/version.py
rctuiautomator2/watcher.py
rctuiautomator2/webview.py
rctuiautomator2/widget.py
rctuiautomator2/xpath.py
rctuiautomator2/ext/__init__.py
rctuiautomator2/ext/htmlreport/README.md
rctuiautomator2/ext/htmlreport/__init__.py
rctuiautomator2/ext/htmlreport/assets/index.html
rctuiautomator2/ext/htmlreport/assets/pig.jpg
rctuiautomator2/ext/htmlreport/assets/simplehttpserver.py
rctuiautomator2/ext/htmlreport/assets/start.bat
rctuiautomator2/ext/info/__init__.py
rctuiautomator2/ext/info/conf.py
rctuiautomator2/ext/perf/README.md
rctuiautomator2/ext/perf/__init__.py
rctuiautomator2/ext/perf/net.png
rctuiautomator2/ext/perf/summary.png
rctuiautomator2/ext/xpath/README.md
rctuiautomator2/ext/xpath/__init__.py
rctuiautomator2/ext-archived/aircv/README.md
rctuiautomator2/ext-archived/aircv/__init__.py
rctuiautomator2/ext-archived/ocr/README.md
rctuiautomator2/ext-archived/ocr/__init__.py
rctuiautomator2/ext-archived/ocr/baiduOCR.py
rctuiautomator2-2.16.1.dev5.dist-info/AUTHORS
rctuiautomator2-2.16.1.dev5.dist-info/LICENSE
rctuiautomator2-2.16.1.dev5.dist-info/METADATA
rctuiautomator2-2.16.1.dev5.dist-info/WHEEL
rctuiautomator2-2.16.1.dev5.dist-info/entry_points.txt
rctuiautomator2-2.16.1.dev5.dist-info/pbr.json
rctuiautomator2-2.16.1.dev5.dist-info/top_level.txt
rctuiautomator2-2.16.1.dev5.dist-info/RECORD
