Metadata-Version: 2.1
Name: rctuiautomator2
Version: 2.16.1.dev5
Summary: Python Wrapper for Google Android UiAutomator2 test tool
Home-page: https://github.com/rct-ai/uiautomator2
Author: shendezhou
Author-email: shendezhou@rct.ai
License: MIT
Platform: UNKNOWN
Classifier: Development Status :: 4 - Beta
Classifier: Environment :: Console
Classifier: Intended Audience :: Developers
Classifier: Operating System :: POSIX
Classifier: Programming Language :: Python :: 3
Classifier: Topic :: Software Development :: Libraries :: Python Modules
Classifier: Topic :: Software Development :: Testing
Requires-Python: >=3.6
License-File: LICENSE
License-File: AUTHORS
Requires-Dist: six
Requires-Dist: requests
Requires-Dist: whichcraft
Requires-Dist: logzero (~=1.5)
Requires-Dist: progress (~=1.3)
Requires-Dist: retry (~=0.9)
Requires-Dist: adbutils (<1.0,>=0.11.0)
Requires-Dist: Deprecated (~=1.2.6)
Requires-Dist: Pillow
Requires-Dist: lxml (>=4.3)
Requires-Dist: cached-property (<2.0,>=1.5.1)
Requires-Dist: packaging (~=20.3)
Provides-Extra: image
Requires-Dist: scikit-image ; extra == 'image'
Requires-Dist: imutils ; extra == 'image'
Requires-Dist: findit ; extra == 'image'
Requires-Dist: imageio (<3.0,>=2.8.0) ; extra == 'image'
Requires-Dist: imageio-ffmpeg (<1.0,>=0.4.2) ; extra == 'image'
Requires-Dist: websocket-client (<1.0,>=0.57.0) ; extra == 'image'
